LICENSE
MANIFEST.in
README.md
VERSION
pyproject.toml
requirements.txt
setup.py
covalent_dask_plugin/__init__.py
covalent_dask_plugin/dask.py
covalent_dask_plugin.egg-info/PKG-INFO
covalent_dask_plugin.egg-info/SOURCES.txt
covalent_dask_plugin.egg-info/dependency_links.txt
covalent_dask_plugin.egg-info/entry_points.txt
covalent_dask_plugin.egg-info/requires.txt
covalent_dask_plugin.egg-info/top_level.txt
tests/__init__.py
tests/functional_test.py
tests/plugin_test.py