Metadata-Version: 2.1
Name: covalent-dask-plugin
Version: 0.3.0
Summary: Covalent Dask Plugin
Home-page: https://github.com/AgnostiqHQ/covalent-dask-plugin
Download-URL: https://github.com/AgnostiqHQ/covalent-dask-plugin/archive/v0.3.0.tar.gz
Author: Agnostiq
Author-email: support@agnostiq.ai
Maintainer: Agnostiq
License: GNU Affero GPL v3.0
Classifier: Development Status :: 3 - Alpha
Classifier: Environment :: Console
Classifier: Environment :: Plugins
Classifier: Intended Audience :: Developers
Classifier: Intended Audience :: Education
Classifier: Intended Audience :: Science/Research
Classifier: License :: Other/Proprietary License
Classifier: Natural Language :: English
Classifier: Operating System :: MacOS
Classifier: Operating System :: POSIX :: Linux
Classifier: Programming Language :: Python :: 3
Classifier: Programming Language :: Python :: 3 :: Only
Classifier: Programming Language :: Python :: 3.8
Classifier: Programming Language :: Python :: 3.9
Classifier: Topic :: Adaptive Technologies
Classifier: Topic :: Scientific/Engineering
Classifier: Topic :: Scientific/Engineering :: Interface Engine/Protocol Translator
Classifier: Topic :: Software Development
Classifier: Topic :: System :: Distributed Computing
License-File: LICENSE
